vra_sdk/__init__.py
vra_sdk/vra_authenticate.py
vra_sdk/vra_config.py
vra_sdk/vra_decorator.py
vra_sdk/vra_exceptions.py
vra_sdk/vra_factory.py
vra_sdk/vra_formatter.py
vra_sdk/vra_request.py
vra_sdk/vra_sdk.py
vra_sdk/vra_utils.py
vra_sdk/models/__init__.py
vra_sdk/models/vra_object.py
vra_sdk/models/vra_payload_6.py
vra_sdk/models/vra_payload_7.py
vra_sdk-1.1.0.dist-info/LICENCE
vra_sdk-1.1.0.dist-info/METADATA
vra_sdk-1.1.0.dist-info/WHEEL
vra_sdk-1.1.0.dist-info/top_level.txt
vra_sdk-1.1.0.dist-info/RECORD
