Metadata-Version: 2.1
Name: vra-sdk
Version: 1.1.0
Summary: vra_sdk
Home-page: https://github.com/richarddevers/vra_sdk
Author: Richard DEVERS
Author-email: ritchiedev25@gmail.com
License: MIT
Platform: UNKNOWN
Requires-Dist: pbr
Requires-Dist: requests
Requires-Dist: dateutils
Requires-Dist: urllib3
